costsekondi/__init__.py
costsekondi/__main__.py
costsekondi/authenticate.py
costsekondi-0.0.1.dist-info/METADATA
costsekondi-0.0.1.dist-info/WHEEL
costsekondi-0.0.1.dist-info/dependency_links.txt
costsekondi-0.0.1.dist-info/entry_points.txt
costsekondi-0.0.1.dist-info/top_level.txt
costsekondi-0.0.1.dist-info/RECORD
