Metadata-Version: 2.1
Name: costsekondi
Version: 0.0.1
Summary: A CLI tool for CoST Sekondi-Takoradi in Ghana West Africa to make the general public access their Infrastructure Transparency Initiative data
Home-page: https://costsekondi-takoradigh.org/
Author: LoGig
Author-email: inquiries@logig.tech
License: MIT
Download-URL: https://costsekondi-takoradigh.org/
Platform: UNKNOWN
Classifier: License :: OSI Approved :: MIT License
Classifier: Programming Language :: Python :: 2.7
Classifier: Programming Language :: Python :: 3
Classifier: Programming Language :: Python :: 3.7
Requires-Python: >=3
Requires-Dist: appdirs (==1.4.4)
Requires-Dist: backports.functools-lru-cache (==1.6.1)
Requires-Dist: beautifulsoup4 (==4.9.3)
Requires-Dist: bleach (==3.2.3)
Requires-Dist: certifi (==2020.12.5)
Requires-Dist: chardet (==4.0.0)
Requires-Dist: click (==7.1.2)
Requires-Dist: colorama (==0.4.4)
Requires-Dist: costsekondi (==0.0.1)
Requires-Dist: distlib (==0.3.1)
Requires-Dist: docutils (==0.16)
Requires-Dist: filelock (==3.0.12)
Requires-Dist: idna (==2.10)
Requires-Dist: keyring (==22.0.1)
Requires-Dist: lxml (==4.6.2)
Requires-Dist: packaging (==20.8)
Requires-Dist: pathlib (==1.0.1)
Requires-Dist: pbr (==5.5.1)
Requires-Dist: pkginfo (==1.7.0)
Requires-Dist: Pygments (==2.7.4)
Requires-Dist: pyparsing (==2.4.7)
Requires-Dist: readme-renderer (==28.0)
Requires-Dist: requests (==2.25.1)
Requires-Dist: requests-toolbelt (==0.9.1)
Requires-Dist: rfc3986 (==1.4.0)
Requires-Dist: six (==1.15.0)
Requires-Dist: soupsieve (==2.1)
Requires-Dist: stevedore (==3.3.0)
Requires-Dist: tqdm (==4.56.0)
Requires-Dist: twine (==1.15.0)
Requires-Dist: urllib3 (==1.26.3)
Requires-Dist: virtualenv (==20.4.0)
Requires-Dist: virtualenv-clone (==0.5.4)
Requires-Dist: virtualenvwrapper (==4.8.4)
Requires-Dist: webencodings (==0.5.1)
